opentelemetry_mcp/__init__.py
opentelemetry_mcp/attributes.py
opentelemetry_mcp/config.py
opentelemetry_mcp/constants.py
opentelemetry_mcp/models.py
opentelemetry_mcp/server.py
opentelemetry_mcp/utils.py
opentelemetry_mcp/backends/__init__.py
opentelemetry_mcp/backends/base.py
opentelemetry_mcp/backends/filter_engine.py
opentelemetry_mcp/backends/jaeger.py
opentelemetry_mcp/backends/tempo.py
opentelemetry_mcp/backends/traceloop.py
opentelemetry_mcp/tools/__init__.py
opentelemetry_mcp/tools/errors.py
opentelemetry_mcp/tools/expensive_traces.py
opentelemetry_mcp/tools/list_llm_tools.py
opentelemetry_mcp/tools/list_models.py
opentelemetry_mcp/tools/model_stats.py
opentelemetry_mcp/tools/search.py
opentelemetry_mcp/tools/search_spans.py
opentelemetry_mcp/tools/services.py
opentelemetry_mcp/tools/slow_traces.py
opentelemetry_mcp/tools/trace.py
opentelemetry_mcp/tools/usage.py
opentelemetry_mcp-0.2.0.dist-info/METADATA
opentelemetry_mcp-0.2.0.dist-info/WHEEL
opentelemetry_mcp-0.2.0.dist-info/entry_points.txt
opentelemetry_mcp-0.2.0.dist-info/licenses/LICENSE
opentelemetry_mcp-0.2.0.dist-info/RECORD
