Metadata-Version: 2.4
Name: opentelemetry-mcp
Version: 0.2.0
Summary: MCP server for querying OpenTelemetry traces from LLM applications with Opentelemetry support
Project-URL: Homepage, https://github.com/traceloop/opentelemetry-mcp-server
Project-URL: Documentation, https://github.com/traceloop/opentelemetry-mcp-server#readme
Project-URL: Repository, https://github.com/traceloop/opentelemetry-mcp-server
Project-URL: Issues, https://github.com/traceloop/opentelemetry-mcp-server/issues
Project-URL: Changelog, https://github.com/traceloop/opentelemetry-mcp-server/blob/main/CHANGELOG.md
Author-email: Doron Kopit <doron@traceloop.com>, Gal Klienman <gal@traceloop.com>, Nir Gazit <nir@traceloop.com>
License: Apache-2.0
License-File: LICENSE
Keywords: debugging,jaeger,llm,mcp,model-context-protocol,observability,opentelemetry,telemetry,tempo,traceloop,tracing
Classifier: Development Status :: 4 - Beta
Classifier: Framework :: FastAPI
Classifier: Intended Audience :: Developers
Classifier: Programming Language :: Python :: 3
Classifier: Programming Language :: Python :: 3.11
Classifier: Programming Language :: Python :: 3.12
Classifier: Programming Language :: Python :: 3.13
Classifier: Topic :: Software Development :: Libraries :: Python Modules
Classifier: Topic :: System :: Monitoring
Requires-Python: >=3.11
Requires-Dist: click~=8.3.0
Requires-Dist: fastmcp~=2.13.0
Requires-Dist: httpx~=0.28.0
Requires-Dist: mcp~=1.20.0
Requires-Dist: opentelemetry-semantic-conventions-ai>=0.4.0
Requires-Dist: opentelemetry-semantic-conventions>=0.48b0
Requires-Dist: pydantic~=2.12.0
Requires-Dist: python-dotenv~=1.2.0
Requires-Dist: starlette~=0.50.0
Requires-Dist: uvicorn~=0.38.0
